owntwin/__init__.py
owntwin/builder/__init__.py
owntwin/builder/cli.py
owntwin/builder/commands.py
owntwin/builder/package.py
owntwin/builder/render.py
owntwin/builder/terrain.py
owntwin/builder/tile.py
owntwin/builder/utils.py
owntwin/builtin_datasources/gsi.py
owntwin/builtin_datasources/gsi_disaportal.py
owntwin/builtin_modules/base/__init__.py
owntwin/cli.py
owntwin/sample_modules/bousai/__init__.py
owntwin/sample_modules/bousai_tokyo/__init__.py
owntwin/sample_modules/jpsearch/__init__.py
owntwin/sample_modules/plateau/__init__.py
owntwin/viewer/__init__.py
owntwin/viewer/owntwin/favicon.svg
owntwin/viewer/owntwin/index.html
owntwin/viewer/owntwin/static/index-08576e29.css
owntwin/viewer/owntwin/static/index-cd5749f0.js
owntwin-0.2.0.dist-info/LICENSE.txt
owntwin-0.2.0.dist-info/METADATA
owntwin-0.2.0.dist-info/WHEEL
owntwin-0.2.0.dist-info/entry_points.txt
owntwin-0.2.0.dist-info/RECORD
